sphinxcontrib/__init__.py
sphinxcontrib/diagrams.py
sphinxcontrib_diagrams-0.1.4.dist-info/WHEEL
sphinxcontrib_diagrams-0.1.4.dist-info/METADATA
sphinxcontrib_diagrams-0.1.4.dist-info/RECORD
