Metadata-Version: 2.1
Name: sphinxcontrib-diagrams
Version: 0.1.4
Summary: 
Author: yamionp
Author-email: yami@crimsondream.jp
Requires-Python: >=3.6,<4.0
Classifier: Programming Language :: Python :: 3
Classifier: Programming Language :: Python :: 3.10
Classifier: Programming Language :: Python :: 3.6
Classifier: Programming Language :: Python :: 3.7
Classifier: Programming Language :: Python :: 3.8
Classifier: Programming Language :: Python :: 3.9
Requires-Dist: sphinx (>=4.3)
